sy_a/__init__.py
sy_a/ba.py
sy_a/cb.py
sy_a/actor/__init__.py
tests/__init__.py
tests/test_0.py
sy_a-0.0.1.post0.dist-info/LICENSE
sy_a-0.0.1.post0.dist-info/METADATA
sy_a-0.0.1.post0.dist-info/WHEEL
sy_a-0.0.1.post0.dist-info/top_level.txt
sy_a-0.0.1.post0.dist-info/RECORD
