Metadata-Version: 2.1
Name: sy-a
Version: 0.0.1.post0
Summary: My package description
Home-page: UNKNOWN
License: BSD 3-Clause License
Keywords: one,two
Platform: UNKNOWN
Classifier: Framework :: Django
Classifier: License :: OSI Approved :: BSD License
Classifier: Programming Language :: Python :: 3
Classifier: Programming Language :: Python :: 3.5
